[
    {
        "benchmark": "apparat",
        "stdev(%)": 3.9448323217713197,
        "RMAD(%)": 1.4955951649252204,
        "avg time": 2474.19,
        "median": 2440.5,
        "normal distribution": false
    },
    {
        "benchmark": "factorie",
        "stdev(%)": 2.697966664224981,
        "RMAD(%)": 2.2636600173460537,
        "avg time": 5772.06,
        "median": 5765.0,
        "normal distribution": false
    },
    {
        "benchmark": "kiama",
        "stdev(%)": 7.805499909721517,
        "RMAD(%)": 4.0650406504065035,
        "avg time": 126.66,
        "median": 123.0,
        "normal distribution": false
    },
    {
        "benchmark": "scalac",
        "stdev(%)": 1.5274645539653993,
        "RMAD(%)": 0.4464285714285714,
        "avg time": 449.13,
        "median": 448.0,
        "normal distribution": false
    },
    {
        "benchmark": "scaladoc",
        "stdev(%)": 0.6556653139883238,
        "RMAD(%)": 0.47393364928909953,
        "avg time": 422.3,
        "median": 422.0,
        "normal distribution": false
    },
    {
        "benchmark": "scalap",
        "stdev(%)": 1.172198429440458,
        "RMAD(%)": 0.0,
        "avg time": 42.56,
        "median": 43.0,
        "normal distribution": false
    },
    {
        "benchmark": "scalariform",
        "stdev(%)": 1.6571664524284027,
        "RMAD(%)": 0.7518796992481203,
        "avg time": 133.01,
        "median": 133.0,
        "normal distribution": false
    },
    {
        "benchmark": "scalaxb",
        "stdev(%)": 2.50339569399184,
        "RMAD(%)": 1.4492753623188406,
        "avg time": 137.71,
        "median": 138.0,
        "normal distribution": false
    },
    {
        "benchmark": "tmt",
        "stdev(%)": 0.5619365448011779,
        "RMAD(%)": 0.32492354740061163,
        "avg time": 2616.79,
        "median": 2616.0,
        "normal distribution": false
    }
]