[
    {
        "benchmark": "akka-uct",
        "stdev(%)": 9.721063537001518,
        "RMAD(%)": 6.863752907875925,
        "avg time": 39274.17649,
        "median": 38582.500499999995,
        "normal distribution": false
    },
    {
        "benchmark": "finagle-http",
        "stdev(%)": 0.5890031996049924,
        "RMAD(%)": 0.34731527721691663,
        "avg time": 5082.57099,
        "median": 5080.2545,
        "normal distribution": false
    },
    {
        "benchmark": "fj-kmeans",
        "stdev(%)": 2.0406883207162587,
        "RMAD(%)": 1.192464970251364,
        "avg time": 20088.88791,
        "median": 20123.61,
        "normal distribution": false
    },
    {
        "benchmark": "future-genetic",
        "stdev(%)": 0.14029532383782586,
        "RMAD(%)": 0.10523369448352106,
        "avg time": 2913.65522,
        "median": 2913.5155,
        "normal distribution": true
    },
    {
        "benchmark": "mnemonics",
        "stdev(%)": 1.9608484541828497,
        "RMAD(%)": 0.876451844687862,
        "avg time": 4137.45024,
        "median": 4122.9875,
        "normal distribution": false
    },
    {
        "benchmark": "par-mnemonics",
        "stdev(%)": 3.3401285024536453,
        "RMAD(%)": 1.8059903937060213,
        "avg time": 3402.52067,
        "median": 3367.792,
        "normal distribution": false
    },
    {
        "benchmark": "philosophers",
        "stdev(%)": 1.543042633358865,
        "RMAD(%)": 0.5109141433056373,
        "avg time": 323.13225,
        "median": 324.4185,
        "normal distribution": false
    },
    {
        "benchmark": "reactors",
        "stdev(%)": 11.298859215882977,
        "RMAD(%)": 5.947620197576021,
        "avg time": 20012.65851,
        "median": 19884.802,
        "normal distribution": false
    },
    {
        "benchmark": "rx-scrabble",
        "stdev(%)": 0.520894161448269,
        "RMAD(%)": 0.20746245548846184,
        "avg time": 161.67321,
        "median": 161.475,
        "normal distribution": false
    },
    {
        "benchmark": "scala-doku",
        "stdev(%)": 0.8853688054745873,
        "RMAD(%)": 0.2364846243465951,
        "avg time": 1991.37157,
        "median": 1986.5985,
        "normal distribution": false
    },
    {
        "benchmark": "scala-kmeans",
        "stdev(%)": 0.7055030124834896,
        "RMAD(%)": 0.5483168880871147,
        "avg time": 273.48421,
        "median": 273.83799999999997,
        "normal distribution": false
    },
    {
        "benchmark": "scala-stm-bench7",
        "stdev(%)": 5.9543319975293665,
        "RMAD(%)": 0.8603973916362516,
        "avg time": 1893.86411,
        "median": 1864.0805,
        "normal distribution": false
    },
    {
        "benchmark": "scrabble",
        "stdev(%)": 2.751977473612443,
        "RMAD(%)": 1.2775939710091186,
        "avg time": 1733.61989,
        "median": 1724.335,
        "normal distribution": false
    }
]