[
    {
        "benchmark": "akka-uct",
        "stdev(%)": 4.819977902996362,
        "RMAD(%)": 2.56075700105276,
        "avg time": 15060.89121,
        "median": 15211.498,
        "normal distribution": false
    },
    {
        "benchmark": "finagle-http",
        "stdev(%)": 4.6766968982226915,
        "RMAD(%)": 1.4183634910720753,
        "avg time": 8900.97255,
        "median": 9099.5715,
        "normal distribution": false
    },
    {
        "benchmark": "fj-kmeans",
        "stdev(%)": 0.8306811780800699,
        "RMAD(%)": 0.5227751159462708,
        "avg time": 3354.46368,
        "median": 3349.7195,
        "normal distribution": false
    },
    {
        "benchmark": "future-genetic",
        "stdev(%)": 1.2498530772450238,
        "RMAD(%)": 0.621680606463307,
        "avg time": 1600.19177,
        "median": 1597.5245,
        "normal distribution": false
    },
    {
        "benchmark": "mnemonics",
        "stdev(%)": 0.20181101308926527,
        "RMAD(%)": 0.02270046844787417,
        "avg time": 3766.17467,
        "median": 3764.2394999999997,
        "normal distribution": false
    },
    {
        "benchmark": "par-mnemonics",
        "stdev(%)": 9.798614771910165,
        "RMAD(%)": 0.8438568096502775,
        "avg time": 2597.34033,
        "median": 2476.3680000000004,
        "normal distribution": false
    },
    {
        "benchmark": "philosophers",
        "stdev(%)": 5.623972556978861,
        "RMAD(%)": 2.0366182837982776,
        "avg time": 4009.72694,
        "median": 3993.1144999999997,
        "normal distribution": false
    },
    {
        "benchmark": "reactors",
        "stdev(%)": 3.81716966172611,
        "RMAD(%)": 2.5899359049328816,
        "avg time": 11144.72415,
        "median": 11175.431,
        "normal distribution": true
    },
    {
        "benchmark": "rx-scrabble",
        "stdev(%)": 0.6194843489390776,
        "RMAD(%)": 0.2546174675665826,
        "avg time": 123.80832,
        "median": 123.715,
        "normal distribution": false
    },
    {
        "benchmark": "scala-doku",
        "stdev(%)": 0.9373854716312411,
        "RMAD(%)": 0.20047318174741743,
        "avg time": 1882.04496,
        "median": 1875.812,
        "normal distribution": false
    },
    {
        "benchmark": "scala-kmeans",
        "stdev(%)": 0.6652976935511663,
        "RMAD(%)": 0.4879776402913004,
        "avg time": 274.14023,
        "median": 273.8855,
        "normal distribution": false
    },
    {
        "benchmark": "scala-stm-bench7",
        "stdev(%)": 0.669214430049308,
        "RMAD(%)": 0.23727741709569586,
        "avg time": 1342.45683,
        "median": 1339.3605,
        "normal distribution": false
    },
    {
        "benchmark": "scrabble",
        "stdev(%)": 1.1727959617272916,
        "RMAD(%)": 0.822032351330495,
        "avg time": 169.6458,
        "median": 169.823,
        "normal distribution": true
    }
]