[
    {
        "benchmark": "blackscholes",
        "stdev(%)": 1.3630849801709282,
        "RMAD(%)": 1.4492753623188406,
        "avg time": 693.4,
        "median": 690.0,
        "normal distribution": false
    },
    {
        "benchmark": "bodytrack",
        "stdev(%)": 1.51924023862179,
        "RMAD(%)": 1.1286681715575622,
        "avg time": 6628.8,
        "median": 6645.0,
        "normal distribution": false
    },
    {
        "benchmark": "facesim",
        "stdev(%)": 0.5200757933794699,
        "RMAD(%)": 0.32310177705977383,
        "avg time": 18544.3,
        "median": 18570.0,
        "normal distribution": false
    },
    {
        "benchmark": "ferret",
        "stdev(%)": 0.8091855069900761,
        "RMAD(%)": 0.5428881650380022,
        "avg time": 9236.1,
        "median": 9210.0,
        "normal distribution": false
    },
    {
        "benchmark": "fluidanimate",
        "stdev(%)": 1.223251298107728,
        "RMAD(%)": 0.4437869822485207,
        "avg time": 6731.9,
        "median": 6760.0,
        "normal distribution": false
    },
    {
        "benchmark": "freqmine",
        "stdev(%)": 1.8628678241992551,
        "RMAD(%)": 0.9584664536741214,
        "avg time": 3144.1,
        "median": 3130.0,
        "normal distribution": false
    },
    {
        "benchmark": "swaptions",
        "stdev(%)": 1.5318933571811075,
        "RMAD(%)": 0.7889546351084813,
        "avg time": 5101.4,
        "median": 5070.0,
        "normal distribution": false
    },
    {
        "benchmark": "vips",
        "stdev(%)": 1.6895965124012209,
        "RMAD(%)": 1.645021645021645,
        "avg time": 5787.3,
        "median": 5775.0,
        "normal distribution": false
    }
]